seo/__init__.py
seo/settings.py
seo/storage.py
seo/utils.py
seo/ville/__init__.py
seo/ville/slugger.py
seo/ville/sorl.py
seo_ville_slugger-0.0.7.dist-info/LICENSE
seo_ville_slugger-0.0.7.dist-info/METADATA
seo_ville_slugger-0.0.7.dist-info/WHEEL
seo_ville_slugger-0.0.7.dist-info/top_level.txt
seo_ville_slugger-0.0.7.dist-info/RECORD
