Metadata-Version: 2.1
Name: seo-ville-slugger
Version: 0.0.7
Summary: This storage backend stores files named after their hash value and adds a symlink with the original name. No duplication and you can SEO your heart out.
Home-page: https://github.com/specialunderwear/seo-ville-slugger
Author: Boie ktule
Author-email: boie@permanentmarkers.nl
License: GPL
Platform: UNKNOWN
Requires-Dist: setuptools
Requires-Dist: Django
